django_font_awesome-4.6.1.dist-info/DESCRIPTION.rst
django_font_awesome-4.6.1.dist-info/METADATA
django_font_awesome-4.6.1.dist-info/RECORD
django_font_awesome-4.6.1.dist-info/WHEEL
django_font_awesome-4.6.1.dist-info/metadata.json
django_font_awesome-4.6.1.dist-info/top_level.txt
font_awesome/__init__.py
font_awesome/models.py
font_awesome/static/css/font-awesome.css
font_awesome/static/css/font-awesome.min.css
font_awesome/static/fonts/FontAwesome.otf
font_awesome/static/fonts/fontawesome-webfont.eot
font_awesome/static/fonts/fontawesome-webfont.svg
font_awesome/static/fonts/fontawesome-webfont.ttf
font_awesome/static/fonts/fontawesome-webfont.woff
font_awesome/static/fonts/fontawesome-webfont.woff2
